{
    "Products" :[
        {
            "id" : 1,
            "name" : "Product 01",
            "desc" : "Product Data",
            "price" :  999,
            "color" : "#ffffff",
            "image" : "https://image.shutterstock.com/image-photo/surgut-russia-june-20-2020-260nw-1759972391.jpg"
        },
        {
            "id" : 2,
            "name" : "Product 02",
            "desc" : "Product Data",
            "price" :  999,
            "color" : "#ffffff",
            "image" : "https://image.shutterstock.com/image-photo/surgut-russia-june-20-2020-260nw-1759972391.jpg"
        },
        {
            "id" : 3,
            "name" : "Product 03",
            "desc" : "Product Data",
            "price" :  999,
            "color" : "#ffffff",
            "image" : "https://image.shutterstock.com/image-photo/surgut-russia-june-20-2020-260nw-1759972391.jpg"
        },
        {
            "id" : 4,
            "name" : "Product 04",
            "desc" : "Product Data",
            "price" :  999,
            "color" : "#ffffff",
            "image" : "https://image.shutterstock.com/image-photo/surgut-russia-june-20-2020-260nw-1759972391.jpg"
        },
        {
            "id" : 5,
            "name" : "Product 05",
            "desc" : "Product Data",
            "price" :  999,
            "color" : "#ffffff",
            "image" : "https://image.shutterstock.com/image-photo/surgut-russia-june-20-2020-260nw-1759972391.jpg"
        },
        {
            "id" : 6,
            "name" : "Product 06",
            "desc" : "Product Data",
            "price" :  999,
            "color" : "#ffffff",
            "image" : "https://encrypted-tbn0.gstatic.com/images?q=tbn:ANd9GcSLQynsPTPqe4uUzyfAAUSjxlYZkCyPz-h4cw&usqp=CAU"
        },
        {
            "id" : 7,
            "name" : "Product 08",
            "desc" : "Product Data",
            "price" :  999,
            "color" : "#ffffff",
            "image" : "https://ss7.vzw.com/is/image/VerizonWireless/apple-watch-series-7-lte-41mm-midnight-aluminum-midnight-sport-band-mkh73ll-a-sku4790160"
        },
        {
            "id" : 8,
            "name" : "Product 09",
            "desc" : "Product Data",
            "price" :  999,
            "color" : "#ffffff",
            "image" : "https://encrypted-tbn0.gstatic.com/images?q=tbn:ANd9GcSLQynsPTPqe4uUzyfAAUSjxlYZkCyPz-h4cw&usqp=CAU"
        },
        {
            "id" : 9,
            "name" : "Product 08",
            "desc" : "Product Data",
            "price" :  999,
            "color" : "#ffffff",
            "image" : "https://image.shutterstock.com/image-photo/surgut-russia-june-20-2020-260nw-1759972391.jpg"
        },
        {
            "id" : 10,
            "name" : "Product 09",
            "desc" : "Product Data",
            "price" :  999,
            "color" : "#ffffff",
            "image" : "https://image.shutterstock.com/image-photo/surgut-russia-june-20-2020-260nw-1759972391.jpg"
        }
    ]
}